[
    {
        "text": "Récépissé",
        "left": 5,
        "top": 200.881,
        "style": "QRInvoiceMainTitleTextStyle"
    },
    {
        "text": "Compte / Payable à",
        "left": 5,
        "top": 206.117,
        "style": "QRInvoiceReceiptHeaderTextStyle"
    },
    {
        "text": "Référence",
        "left": 5,
        "top": 225.167,
        "style": "QRInvoiceReceiptHeaderTextStyle"
    },
    {
        "text": "Payable par",
        "left": 5,
        "top": 234.692,
        "style": "QRInvoiceReceiptHeaderTextStyle"
    },
    {
        "text": "Monnaie",
        "left": 5,
        "top": 262.117,
        "style": "QRInvoiceReceiptHeaderTextStyle"
    },
    {
        "text": "Montant",
        "left": 20,
        "top": 262.117,
        "style": "QRInvoiceReceiptHeaderTextStyle"
    },
    {
        "text": "Point de dépôt",
        "left": 57,
        "top": 276.117,
        "style": "QRInvoiceReceiptHeaderRightTextStyle"
    }
]
